crystal_functions/__init__.py
crystal_functions/adsorb.py
crystal_functions/calculate.py
crystal_functions/convert.py
crystal_functions/execute.py
crystal_functions/file_readwrite.py
crystal_functions/plot.py
crystal_functions/thermodynamics.py
crystal_functions/unit_test.py
crystal_functions/units.py
crystal_functions/utils.py
crystal_functions-2022.12.27.dist-info/LICENSE.txt
crystal_functions-2022.12.27.dist-info/METADATA
crystal_functions-2022.12.27.dist-info/WHEEL
crystal_functions-2022.12.27.dist-info/top_level.txt
crystal_functions-2022.12.27.dist-info/RECORD
