Metadata-Version: 2.1
Name: crystal-functions
Version: 2022.12.27
Summary: Functions to be used with the CRYSTAL code.
Home-page: https://github.com/crystal-code-tools/crystal_functions
Author-email: crystalcodetools@gmail.com
Project-URL: Bug Tracker, https://github.com/crystal-code-tools/crystal_functions/issues
Classifier: Programming Language :: Python :: 3
Classifier: License :: OSI Approved :: MIT License
Classifier: Operating System :: OS Independent
License-File: LICENSE.txt
Requires-Dist: pymatgen
Requires-Dist: mendeleev
Requires-Dist: ase
